realestatebot/__init__.py
realestatebot-0.0.2.dist-info/LICENSE
realestatebot-0.0.2.dist-info/METADATA
realestatebot-0.0.2.dist-info/WHEEL
realestatebot-0.0.2.dist-info/top_level.txt
realestatebot-0.0.2.dist-info/zip-safe
realestatebot-0.0.2.dist-info/RECORD
