Metadata-Version: 2.1
Name: realestatebot
Version: 0.0.2
Summary: (it's free real estate)
Home-page: https://github.com/silvncr/realestatebot
Author: silvncr
License: MIT
Classifier: Development Status :: 2 - Pre-Alpha
Classifier: Intended Audience :: Developers
Classifier: Intended Audience :: Education
Classifier: Intended Audience :: End Users/Desktop
Classifier: License :: OSI Approved :: MIT License
Classifier: Programming Language :: Python
Classifier: Programming Language :: Python :: 3
Classifier: Topic :: Software Development :: Libraries
Classifier: Topic :: Software Development :: Libraries :: Python Modules
Requires-Python: >=3.12
License-File: LICENSE
Requires-Dist: alive-progress ==3.1.5
Requires-Dist: pandas ==2.2.2
Requires-Dist: python-dotenv ==1.0.1
Requires-Dist: realestate-data ==0.1.0
Requires-Dist: requests ==2.32.3
